harmonicseries/__init__.py
harmonicseries/harmonic.py
harmonicseries-0.0.3.dist-info/METADATA
harmonicseries-0.0.3.dist-info/WHEEL
harmonicseries-0.0.3.dist-info/top_level.txt
harmonicseries-0.0.3.dist-info/RECORD
